func2cli/__init__.py
func2cli/_classes.py
func2cli/_utils.py
func2cli-0.4.0.dist-info/LICENSE
func2cli-0.4.0.dist-info/WHEEL
func2cli-0.4.0.dist-info/METADATA
func2cli-0.4.0.dist-info/RECORD
