Metadata-Version: 2.1
Name: func2cli
Version: 0.4.0
Summary: Automatic CLIs from functions and their docstrings.
Author-email: Dave Connelly <dsconnelly@nyu.edu>
Classifier: License :: OSI Approved :: MIT License
Project-URL: Home, https://github.com/dsconnelly/func2cli
